LICENSE
README.md
pyproject.toml
hposuite/__init__.py
hposuite/__main__.py
hposuite/constants.py
hposuite/exceptions.py
hposuite/register.py
hposuite/run.py
hposuite/study.py
hposuite/utils.py
hposuite.egg-info/PKG-INFO
hposuite.egg-info/SOURCES.txt
hposuite.egg-info/dependency_links.txt
hposuite.egg-info/requires.txt
hposuite.egg-info/top_level.txt
hposuite/benchmarks/__init__.py
hposuite/benchmarks/__main__.py
hposuite/benchmarks/bbob.py
hposuite/benchmarks/bbob_tabular.py
hposuite/benchmarks/create_tabular.py
hposuite/benchmarks/lcbench_tabular.py
hposuite/benchmarks/mfh_tabular.py
hposuite/benchmarks/mfp_bench.py
hposuite/benchmarks/pymoo.py
hposuite/benchmarks/synthetic.py
hposuite/optimizers/__init__.py
hposuite/optimizers/__main__.py
hposuite/optimizers/dehb.py
hposuite/optimizers/hebo.py
hposuite/optimizers/neps_optimizers.py
hposuite/optimizers/nevergrad.py
hposuite/optimizers/optuna.py
hposuite/optimizers/random_search.py
hposuite/optimizers/scikit_optimize.py
hposuite/optimizers/smac.py
hposuite/optimizers/synetune.py
hposuite/plotting/__init__.py
hposuite/plotting/incumbent_trace.py
hposuite/plotting/styles.py
hposuite/plotting/utils.py