Metadata-Version: 2.4
Name: hposuite
Version: 0.1.2
Summary: A lightweight framework for benchmarking HPO algorithms
Author-email: Soham Basu <soham.basu07@gmail.com>, Eddie Bergman <eddiebergmanhs@gmail.com>, Neeratyoy Malik <neeratyoy@gmail.com>
License: BSD 3-Clause License
Project-URL: source, https://github.com/automl/hposuite/
Classifier: Intended Audience :: Science/Research
Classifier: Intended Audience :: Developers
Classifier: License :: OSI Approved :: BSD License
Classifier: Programming Language :: Python
Classifier: Topic :: Software Development
Classifier: Topic :: Scientific/Engineering
Classifier: Operating System :: POSIX
Classifier: Operating System :: Unix
Classifier: Operating System :: MacOS
Classifier: Programming Language :: Python :: 3
Classifier: Programming Language :: Python :: 3.10
Requires-Python: >=3.10
License-File: LICENSE
Requires-Dist: hpoglue>=0.2.5
Requires-Dist: pandas<3,>=2
Requires-Dist: matplotlib<4,>=3
Requires-Dist: tqdm
Requires-Dist: more_itertools
Requires-Dist: pyyaml
Requires-Dist: pyarrow
Requires-Dist: ConfigSpace>=1.0
Provides-Extra: dev
Requires-Dist: ruff; extra == "dev"
Requires-Dist: mypy; extra == "dev"
Requires-Dist: pre-commit; extra == "dev"
Provides-Extra: notebook
Requires-Dist: ipykernel; extra == "notebook"
Provides-Extra: all
Requires-Dist: ipykernel; extra == "all"
Requires-Dist: smac; extra == "all"
Requires-Dist: optuna; extra == "all"
Requires-Dist: dehb; extra == "all"
Requires-Dist: scikit-optimize; extra == "all"
Requires-Dist: nevergrad; extra == "all"
Requires-Dist: hebo; extra == "all"
Requires-Dist: neural-pipeline-search>=0.13.0; extra == "all"
Requires-Dist: pymoo; extra == "all"
Requires-Dist: mf-prior-bench[pd1]>=1.10.0; extra == "all"
Requires-Dist: ioh>=0.3.14; extra == "all"
Provides-Extra: optimizers
Requires-Dist: smac; extra == "optimizers"
Requires-Dist: optuna; extra == "optimizers"
Requires-Dist: dehb; extra == "optimizers"
Requires-Dist: scikit-optimize; extra == "optimizers"
Requires-Dist: nevergrad; extra == "optimizers"
Requires-Dist: hebo; extra == "optimizers"
Requires-Dist: neural-pipeline-search>=0.13.0; extra == "optimizers"
Provides-Extra: benchmarks
Requires-Dist: pymoo; extra == "benchmarks"
Requires-Dist: mf-prior-bench[pd1]>=1.10.0; extra == "benchmarks"
Requires-Dist: ioh>=0.3.14; extra == "benchmarks"
Provides-Extra: smac
Requires-Dist: smac; extra == "smac"
Provides-Extra: optuna
Requires-Dist: optuna; extra == "optuna"
Provides-Extra: dehb
Requires-Dist: dehb; extra == "dehb"
Provides-Extra: skopt
Requires-Dist: scikit-optimize; extra == "skopt"
Provides-Extra: nevergrad
Requires-Dist: nevergrad; extra == "nevergrad"
Provides-Extra: hebo
Requires-Dist: hebo; extra == "hebo"
Provides-Extra: neps
Requires-Dist: neural-pipeline-search>=0.13.0; extra == "neps"
Provides-Extra: pymoo
Requires-Dist: pymoo; extra == "pymoo"
Provides-Extra: mfpbench
Requires-Dist: mf-prior-bench[pd1]>=1.10.0; extra == "mfpbench"
Provides-Extra: bbob
Requires-Dist: ioh>=0.3.14; extra == "bbob"
Dynamic: license-file
